{
"census-dwelling": 
{"Area Unit Code (2013 Areas)": "526500", "2013 Census, fuel types used to heat dwellings (total responses),(4) for occupied private dwellings": {"Total dwellings stated": 1068, "Mains Gas": 3, "Electricity": 822, "Total occupied private dwellings": 1161, "Coal": 36, "Bottled Gas": 258, "Solar Power": 12, "Other Fuel(s)": 12, "Not Elsewhere Included(5)": 96, "Wood": 408, "No Fuels Used in this Dwelling": 42}, "Area Unit Description": "Raglan", "2013 Census, occupied private dwelling type ": {"Separate House": 960, "Total occupied private dwellings": 1164, "Other Occupied Private Dwellings(1)": 15, "Two or More Flats/Units/Townhouses/ Apartments/Houses Joined Together": 78, "Occupied Private Dwelling Not Further Defined": 108}, "2013 Census, number of bedrooms, for occupied private dwellings": {"One Bedroom": 81, "Five Bedrooms": 30, "Eight or More Bedrooms": 0, "Two Bedrooms": 279, "Three Bedrooms": 504, "Four Bedrooms": 168, "Seven Bedrooms": 0, "Total occupied private dwellings": 1161, "Mean Number of Bedrooms": 2.8, "Six Bedrooms": 6, "Total dwellings stated": 1074, "Not Elsewhere Included(3)": 90}, "2013 Census, number of rooms, for occupied private dwellings": {"Six Rooms": 291, "Eight or More Rooms": 177, "Total occupied private  dwellings": 1161, "Five Rooms": 219, "Not Elsewhere Included(2)": 99, "One Room": 15, "Total dwellings stated": 1065, "Four Rooms": 138, "Three Rooms": 72, "Seven Rooms": 138, "Two Rooms": 15}, "2013 Census, dwelling record type for occupied dwellings": {"Occupied Private Dwelling": 1164, "Total occupied dwellings": 1173, "Occupied Non-private Dwelling": 9}},
"census-family": 
{"2013 Census, total families in occupied private dwellings": 732, "2013 Census, total family income (grouped),(1)(2)(3) for families in occupied private dwellings": {"$30,001\u2013$50,000": 132, "$70,001\u2013$100,000": 114, "$20,000 or Less": 57, "Median family income ($)(5)(10)": 59100, "$100,001 or More": 141, "Total families in occupied private dwellings": 732, "$20,001\u2013$30,000": 78, "Total families stated": 618, "Not Stated(4)": 111, "$50,001\u2013$70,000": 102}, "Area Unit Code (2013 Areas)": "526500", "Area Unit Description": "Raglan", "2013 Census, family type, for families in occupied private dwellings": {"One parent with child(ren)": 174, "Couple without children": 306, "Couple with child(ren)": 249, "Total families in occupied private dwellings": 732}, "2013 Census, sources of family income,(6)(7)(8)(9) for families in occupied private dwellings": {"Other Sources of Income": 15, "Other Super., Pensions, Annuities": 21, "Domestic Purposes Benefit": 93, "Interest, Dividends, Rent, Other Invest.": 171, "Total families in private occupied dwellings": 732, "Not Stated": 18, "Total families stated": 717, "Invalids Benefit": 33, "Other Govt Benefits, Payments or Pension": 72, "Sickness Benefit": 30, "NZ Superannuation or Veterans Pension": 117, "Wages, Salary, Commissions, Bonuses etc": 489, "Unemployment Benefit": 36, "Student Allowance": 30, "Self-employment or Business": 237, "No Source of Income During That Time": 3, "Payments from a Work Accident Insurer": 24}},
"census-household": 
{"2013 Census, household composition, for households in occupied private dwellings": {"Two-family household (with or without other people)": 15, "Other multi-person household": 39, "Total households stated": 1104, "Household composition unidentifiable": 39, "Total households in occupied private dwellings": 1143, "One-family household (with or without other people)": 702, "One-person household": 351, "Three or more family household (with or without other people)": 3}, "2013 Census, total households in occupied private dwellings": 1143, "2013 Census, number of motor vehicles, for households in occupied private dwellings": {"Two Motor Vehicles": 378, "Total households stated": 1056, "Three or More Motor Vehicles": 93, "Total households in occupied private dwellings": 1143, "No Motor Vehicle": 84, "Not Elsewhere Included(19)": 87, "One Motor Vehicle": 504}, "Area Unit Code (2013 Areas)": "526500", "2013 Census, number of usual residents in household,(1) for households in occupied private dwellings": {"Six Usual Residents": 21, "One Usual Resident": 351, "Five Usual Residents": 51, "Total households in occupied private dwellings": 1146, "Eight or More Usual Residents": 0, "Mean Number of Usual Household Members": 2.3, "Two Usual Residents": 402, "Seven Usual Residents": 9, "Three Usual Residents": 183, "Four Usual Residents": 126}, "2013 Census, weekly rent paid, for households in rented occupied private dwellings(14)": {"Total households in rented occupied private dwellings": 411, "Total households stated": 393, "Not Elsewhere Included(17)": 15, "$250\u2013$299": 114, "$350 and Over": 63, "Median Weekly Rent Paid ($)(16)(18)": 270, "Under $100": 12, "$150\u2013$199": 39, "$100\u2013$149": 21, "$300\u2013$349": 87, "$200\u2013$249": 60}, "2013 Census, sector of landlord, for households in rented occupied private dwellings(14)": {"Not Elsewhere Included(15)": 21, "Total households in rented occupied private dwellings": 411, "Total households stated": 390, "Private Person, Trust or Business": 372, "Other State-Owned Corporation or State-Owned Enterprise or Government Department or Ministry": 9, "Local Authority or City Council": 3, "Housing New Zealand Corporation": 9}, "Area Unit Description": "Raglan", "2013 Census, access to telecommunications(20)(21), for households in occupied private dwellings": {"Total households stated": 1056, "No Access to Telecommunication Systems": 21, "Access to a Cellphone/Mobile Phone": 888, "Access to the Internet": 753, "Total households in occupied private dwellings": 1143, "Not Elsewhere Included(22)": 87, "Access to a Telephone": 840, "Access to a Fax Machine": 117}, "2013 Census, sources of household income,(6)(7)(8)(9) for households in occupied private dwellings": {"Other Super., Pensions, Annuities": 48, "Total households in occupied private dwellings": 1143, "NZ Superannuation or Veterans Pension": 255, "Interest, Dividends, Rent, Other Invest.": 255, "Self-employment or Business": 291, "Student Allowance": 36, "Domestic Purposes Benefit": 99, "Wages, Salary, Commissions, Bonuses etc": 645, "Other Sources of Income": 24, "No Source of Income During That Time": 9, "Other Govt Benefits, Payments or Pension": 84, "Payments from a Work Accident Insurer": 27, "Invalids Benefit": 51, "Total Households Stated": 1059, "Unemployment Benefit": 51, "Not Stated": 81, "Sickness Benefit": 54}, "2013 Census, total household income (grouped),(2)(3)(4) for households in occupied private dwellings": {"$30,001\u2013$50,000": 198, "$20,000 or Less": 147, "Total households stated": 927, "$70,001\u2013$100,000": 132, "Total households in occupied private dwellings": 1143, "$50,001\u2013$70,000": 138, "$20,001\u2013$30,000": 141, "$100,001 or More": 171, "Median household income ($)(18)(23)": 47500, "Not Stated(5)": 216}, "2013 Census, tenure of household,(10) for households in occupied private dwellings": {"Dwelling Held in a Family Trust(13)": 126, "Total households stated": 1038, "Dwelling Owned or Partly Owned": 465, "Total households in occupied private dwellings": 1146, "Not Elsewhere Included(11)": 108, "Dwelling Not Owned and Not Held in a Family Trust(12)": 444}},
"census-individual-part-1": 
{"Area Unit Description": "Raglan", "2013 Census, six languages (total responses)(11), for the census usually resident population count(1)": {"Total people": 2736, "Samoan": 6, "NZ Sign Language": 27, "M\u0101ori": 300, "None (eg too young to talk)(13)": 45, "Not Elsewhere Included(12)": 219, "English": 2451, "Other": 189, "Total people stated": 2520}, "2013 Census, years at usual residence, for the census usually resident population count(1)": {"30 Years or More": 60, "Total people stated": 2502, "15\u201329 Years": 291, "10\u201314 Years": 231, "Total people": 2736, "1\u20134 Years": 834, "0 Years": 636, "5\u20139 Years": 453, "Not Elsewhere Included(4)": 234}, "2013 Census, census night population count(2)": 2889, "2013 Census, years since arrival in New Zealand, for the overseas\u2013born census usually resident population count(1)": {"30\u201339 Years": 39, "Total people stated": 495, "Not Elsewhere Included(6)": 18, "20\u201329 Years": 45, "50 Years or More": 39, "0\u20139 Years": 273, "40\u201349 Years": 39, "Total people": 513, "10\u201319 Years": 60}, "2013 Census, M\u0101ori descent, for the census usually resident population count(1)": {"No M\u0101ori Descent": 1614, "M\u0101ori Descent": 744, "Not Elsewhere Included(14)": 321, "Don't Know": 60, "Total people": 2736, "Total people stated": 2415}, "2013 Census, age in broad groups, for the census usually resident population count(1)": {"15\u201364 Years": 1713, "65 years and Over": 441, "Total people": 2736, "Under 15 years": 585}, "2013 Census, census usually resident population count(1)": 2736, "Area Unit Code (2013 Areas)": "526500", "2013 Census, birthplace, for the census usually resident population count(1)": {"Not Elsewhere Included(5)": 201, "Overseas born": 513, "Total people": 2736, "NZ born": 2022, "Total people stated": 2535}, "2013 Census, age in five-year groups, for the census usually resident population count(1)": {"15\u201319 Years": 132, "65 years and Over": 438, "Median Age(3)": 39.7, "35\u201339 Years": 228, "5\u20139 Years": 192, "40\u201344 Years": 195, "10\u201314 Years": 159, "55\u201359 Years": 195, "20\u201324 Years": 102, "0\u20134 Years": 231, "50\u201354 Years": 165, "60\u201364 Years": 153, "Total people": 2736, "30\u201334 Years": 210, "45\u201349 Years": 195, "25\u201329 Years": 138}, "2013 Census, ethnic group (grouped total responses)(7)(8), for the census usually resident population count(1)": {"MELAA(9)": 21, "Pacific Peoples": 72, "Other(10)": 33, "European": 2067, "Not Elsewhere Included": 186, "Total people stated": 2547, "Total people": 2736, "M\u0101ori": 693, "Asian": 57}, "2013 Census, usual residence five years ago (2008) indicator, for the census usually resident population count(1)": {"Total people": 2736, "Elsewhere in New Zealand": 1050, "Not Born Five Years Ago": 231, "No Fixed Abode Five Years Ago": 0, "Same as Usual Residence": 954, "Not Elsewhere Included": 264, "Total people stated": 2475, "Overseas": 237}, "2013 Census, sex, for the census usually resident population count(1)": {"Male": 1311, "Female": 1422, "Total people": 2736}},
"census-individual-part-2": 
{"Area Unit Description": "Raglan", "2013 Census, study participation,(18) for the census usually resident population count aged 15 years and over(1)": {"Full-time Study(19)": 135, "Not Studying": 1650, "Total people": 2154, "Part-time Study(20)": 72, "Not stated": 291, "Total people stated": 1860, "Full-time and Part-time Study": 3}, "2013 Census, legally registered relationship status, for the census usually resident population count aged 15 years and over(1)": {"Married (not separated)": 741, "Never married and never in a civil union": 708, "Separated/divorced or dissolved/widowed/surviving partner(6)(7)(8)": 453, "Total people stated": 1902, "Total people": 2151, "Not Elsewhere Included(9)": 252}, "2013 Census, highest qualification,(15) for the census usually resident population count aged 15 years and over(1)": {"Level 4 Certificate": 201, "Doctorate Degree": 30, "Masters Degree": 60, "Level 2 Certificate": 204, "Total people stated": 1869, "Overseas Secondary School Qualification": 87, "Level 1 Certificate": 234, "Bachelor Degree and Level 7 Qualifications": 273, "Level 3 Certificate": 120, "Postgraduate and Honours Degrees": 69, "No Qualification": 396, "Total people": 2154, "Not Elsewhere Included(17)": 285, "Level 5 or Level 6 Diploma(16)": 192}, "2013 Census, number of children born alive,(13) for the female census usually resident population count aged 15 years and over(1)": {"Five Children": 36, "Object to Answering": 33, "One Child": 144, "Not Elsewhere Included(14)": 96, "Four Children": 93, "Six or More Children": 39, "No Children": 282, "Total people stated": 1056, "Three Children": 168, "Two Children": 261, "Total people": 1149}, "2013 Census, tenure holder,(10) for the census usually resident population count aged 15 years and over(1)": {"Not Elsewhere Included(12)": 165, "Own or Partly Own Usual Residence(11)": 972, "Total people stated": 1989, "Do Not Own Usual Residence": 1017, "Total people": 2154}, "Area Unit Code (2013 Areas)": "526500", "2013 Census, total personal income (grouped),(21)(22) for the census usually resident population count aged 15 years and over(1)": {"$5,000 or Less": 234, "$30,001\u2013$50,000": 366, "$5,001\u2013$10,000": 108, "Median personal income ($)(23)(27)": 24900, "Total people": 2151, "Total people stated": 1890, "$20,001\u2013$30,000": 306, "Not stated": 264, "$50,001 or More": 438, "$10,001\u2013$20,000": 432}, "2013 Census, partnership status in current relationship, for the census usually resident population count aged 15 years and over(1)": {"Total people": 2154, "Partnered": 1137, "Not stated": 195, "Total people stated": 1956, "Non-Partnered": 822}, "2013 Census, cigarette smoking behaviour,(4) for the census usually resident population count aged 15 years and over(1)": {"Not Elsewhere Included(5)": 240, "Regular Smoker": 333, "Total people stated": 1914, "Total people": 2151, "Ex-Smoker": 606, "Never Smoked Regularly": 975}, "2013 Census, sources of personal income(24)(25)(26) for the census usually resident population count aged 15 years and over": {"Self-employment or Business": 381, "Wages, Salary, Commissions, Bonuses etc": 1002, "Other Sources of Income": 24, "Total people Stated": 1953, "No Source of Income During That Time": 120, "Not stated": 201, "Sickness Benefit": 69, "Total people": 2154, "Invalids Benefit": 69, "NZ Superannuation or Veterans Pension": 384, "Payments from a Work Accident Insurer": 27, "Other Super., Pensions, Annuities": 57, "Other Govt Benefits, Payments or Pension": 96, "Domestic Purposes Benefit": 102, "Unemployment Benefit": 63, "Student Allowance": 42, "Interest, Dividends, Rent, Other Invest.": 372}, "2013 Census, religious affiliation (total responses),(2) for the census usually resident population count(1)": {"Object to Answering": 129, "Judaism/ Jewish": 3, "Hindu": 15, "Islam/Muslim": 0, "Total people stated": 2466, "Total people": 2736, "Buddhist": 36, "Not Elsewhere Included(3)": 273, "No Religion": 1347, "M\u00e4ori Christian": 30, "Other Religions": 42, "Spiritualism and New Age Religions": 24, "Christian": 903}},
"census-individual-part-3a": 
{"2013 Census, occupation (NZSCO99 major group),(11)(12) for workplace address,(9)(10) for the employed census usually resident population count aged 15 years and over(1)": {"Legislators, Administrators and Managers": 117, "Clerks": 63, "Plant and Machine Operators and Assemblers": 18, "Service and Sales Workers": 174, "Agriculture and Fishery Workers": 12, "Professionals": 174, "Elementary Occupations (incl Residuals)(13)": 51, "Technicians and Associate Professionals": 123, "Total people(14)": 786, "Trades Workers": 54}, "2013 Census, work and labour force status,(2) for the census usually resident population count aged 15 years and over(1)": {"Not in the Labour Force": 750, "Unemployed": 87, "Employed Part-time": 315, "Total people": 2154, "Total people stated": 2022, "Work and Labour Force Status Unidentifiable": 132, "Employed Full-time": 867}, "2013 Census, occupation (NZSCO99 major group),(11)(12) for the employed census usually resident population count aged 15 years and over(1)": {"Legislators, Administrators and Managers": 186, "Clerks": 81, "Plant and Machine Operators and Assemblers": 69, "Service and Sales Workers": 177, "Agriculture and Fishery Workers": 30, "Professionals": 240, "Elementary Occupations (incl Residuals)(13)": 123, "Technicians and Associate Professionals": 195, "Total people(14)": 1185, "Trades Workers": 87}, "2013 Census, occupation (ANZSCO major group),(6)(7) for workplace address,(9)(10) for the employed census usually resident population count aged 15 years and over(1)": {"Technicians and Trades Workers": 99, "Total people": 786, "Not Elsewhere Included(8)": 21, "Total people stated": 765, "Labourers": 63, "Clerical and Administrative Workers": 75, "Sales Workers": 69, "Professionals": 234, "Managers": 111, "Community and Personal Service Workers": 105, "Machinery Operators and Drivers": 6}, "2013 Census, occupation (ANZSCO major group),(6)(7) for the employed census usually resident population count aged 15 years and over(1)": {"Technicians and Trades Workers": 156, "Total people": 1182, "Not Elsewhere Included(8)": 60, "Total people stated": 1122, "Labourers": 114, "Clerical and Administrative Workers": 93, "Sales Workers": 84, "Professionals": 330, "Managers": 192, "Community and Personal Service Workers": 111, "Machinery Operators and Drivers": 33}, "2013 Census, industry (ANZSIC06 division),(15)(16) for the employed census usually resident population count aged 15 years and over(1)": {"Administrative and Support Services": 36, "Total people stated": 1119, "Construction": 102, "Arts and Recreation Services": 21, "Public Administration and Safety": 54, "Transport, Postal and Warehousing": 30, "Not Elsewhere Included(17)": 66, "Mining": 3, "Manufacturing": 87, "Financial and Insurance Services": 15, "Information Media and Telecommunications": 12, "Professional, Scientific and Technical Services": 93, "Rental, Hiring and Real Estate Services": 39, "Electricity, Gas, Water and Waste Services": 21, "Total people": 1182, "Education and Training": 135, "Health Care and Social Assistance": 129, "Other Services": 54, "Wholesale Trade": 36, "Agriculture, Forestry and Fishing": 27, "Accommodation and Food Services": 117, "Retail Trade": 108}, "2013 Census, industry (ANZSIC96 division),(18)(19) for workplace address,(9)(10) for the employed census usually resident population count aged 15 years and over(1)": {"Construction": 39, "Cultural and Recreational Services": 21, "Mining": 0, "Total people stated": 771, "Manufacturing": 45, "Communication Services": 6, "Government Administration and Defence": 21, "Electricity, Gas and Water Supply": 0, "Transport and Storage": 9, "Property and Business Services": 90, "Finance and Insurance": 12, "Personal and Other Services": 36, "Total people": 786, "Accommodation, Cafes and Restaurants": 111, "Not Elsewhere Included(20)": 15, "Wholesale Trade": 6, "Agriculture, Forestry and Fishing": 15, "Retail Trade": 114, "Education": 90, "Health and Community Services": 147}, "Area Unit Description": "Raglan", "2013 Census, status in employment,(3)(4) for the employed census usually resident population count aged 15 years and over(1)": {"Self-Employed and Without Employees": 210, "Paid Employee": 849, "Total people": 1182, "Total people stated": 1152, "Unpaid Family Worker": 21, "Employer": 78, "Not Elsewhere Included(5)": 30}, "2013 Census, industry (ANZSIC96 division),(18)(19) for the employed census usually resident population count aged 15 years and over(1)": {"Property and Business Services": 153, "Cultural and Recreational Services": 30, "Health and Community Services": 132, "Total people stated": 1122, "Manufacturing": 93, "Communication Services": 9, "Government Administration and Defence": 45, "Electricity, Gas and Water Supply": 9, "Mining": 3, "Construction": 93, "Finance and Insurance": 15, "Personal and Other Services": 66, "Total people": 1185, "Accommodation, Cafes and Restaurants": 108, "Not Elsewhere Included(20)": 66, "Wholesale Trade": 36, "Agriculture, Forestry and Fishing": 27, "Retail Trade": 132, "Education": 129, "Transport and Storage": 33}, "2013 Census, industry (ANZSIC06 division),(15)(16) for workplace address,(9)(10) for the employed census usually resident population count aged 15 years and over(1)": {"Administrative and Support Services": 9, "Total people stated": 771, "Construction": 42, "Arts and Recreation Services": 15, "Public Administration and Safety": 24, "Transport, Postal and Warehousing": 9, "Not Elsewhere Included(17)": 15, "Mining": 0, "Manufacturing": 48, "Financial and Insurance Services": 12, "Information Media and Telecommunications": 6, "Professional, Scientific and Technical Services": 60, "Rental, Hiring and Real Estate Services": 33, "Electricity, Gas, Water and Waste Services": 0, "Total people": 783, "Education and Training": 90, "Health Care and Social Assistance": 141, "Other Services": 42, "Wholesale Trade": 6, "Agriculture, Forestry and Fishing": 15, "Accommodation and Food Services": 114, "Retail Trade": 87}, "Area Unit Code (2013 Areas)": "526500"},
"census-individual-part-3b": 
{"2013 Census, hours worked in employment per week,(2)(3) for the employed census usually resident population count aged 15 years and over(1)": {"1\u20139 Hours Worked": 69, "30\u201339 Hours Worked": 189, "Total people stated": 1125, "Not Elsewhere Included(4)": 60, "Total people": 1185, "10\u201319 Hours Worked": 96, "20\u201329 Hours Worked": 135, "40\u201349 Hours Worked": 441, "50\u201359 Hours Worked": 105, "60 Hours or More  Worked": 84}, "Area Unit Code (2013 Areas)": "526500", "2013 Census, main means of travel to work, for the employed census usually resident population count aged 15 years and over(1)": {"Drove a Private Car, Truck or Van": 540, "Total people stated": 1116, "Train": 0, "Motor Cycle or Power Cycle": 9, "Public Bus": 3, "Other": 3, "Total people": 1185, "Worked at Home": 135, "Walked or Jogged": 78, "Drove a Company Car, Truck or Van": 126, "Passenger in a Car, Truck, Van or Company Bus": 42, "Bicycle": 18, "Did Not Go to Work Today": 162, "Not Elsewhere Included(5)": 66}, "Area Unit Description": "Raglan", "2013 Census, unpaid activities(8)(9) for the census usually resident population count aged 15 years and over(1)": {"No Activities": 192, "Total people stated": 1884, "Looking After a Child Who is a Member of Own Household": 567, "Looking After a Child Who Does Not Live in Own Household": 333, "Household Work, Cooking, Repairs, Gardening, etc, for Own Household": 1635, "Looking After a Member of Own Household Who is Ill or Has a Disability": 156, "Helping Someone Who is Ill or Has a Disability Who Does Not Live in Own Household": 213, "Other Helping or Voluntary Work for or Through Any Organisation, Group or Marae": 435, "Total people": 2154, "Not Elsewhere Included(10)": 270}, "2013 Census, main means of travel to work, for workplace address,(6)(7) for the employed census usually resident population count aged 15 years and over(1)": {"Drove a Private Car, Truck or Van": 336, "Total people stated": 762, "Train": 0, "Motor Cycle or Power Cycle": 9, "Public Bus": 0, "Other": 3, "Total people": 786, "Worked at Home": 132, "Walked or Jogged": 78, "Drove a Company Car, Truck or Van": 51, "Passenger in a Car, Truck, Van or Company Bus": 21, "Bicycle": 18, "Did Not Go to Work Today": 114, "Not Elsewhere Included(5)": 24}},
"crime": 
{"Region_2013_label": "Waikato Region", "Index": "350", "Urban_area_type": "Minor urban area", "Urban_area_2013_code": "216", "Area_unit_2013_label": "Raglan", "Urban_area_2013_label": "Raglan", " Rate_per_10000_population ": "62", "Territorial_authority_area_2013_code": "13", "Region_2013_code": "3", " Rate_ratio_NZ_average_rate ": "1.2", "Area_unit_2013_code": "526500", "Territorial_authority_area_2013_label": "Waikato District", "Victimisations_calendar_year_2015": "19", "Population_mid_point_2015": "3070"}}
