{
"census-dwelling": 
{"Area Unit Code (2013 Areas)": "568201", "2013 Census, fuel types used to heat dwellings (total responses),(4) for occupied private dwellings": {"Total dwellings stated": 765, "Mains Gas": 75, "Electricity": 627, "Total occupied private dwellings": 864, "Coal": 33, "Bottled Gas": 129, "Solar Power": 18, "Other Fuel(s)": 15, "Not Elsewhere Included(5)": 99, "Wood": 192, "No Fuels Used in this Dwelling": 30}, "Area Unit Description": "Taita North", "2013 Census, occupied private dwelling type ": {"Separate House": 513, "Total occupied private dwellings": 864, "Other Occupied Private Dwellings(1)": 0, "Two or More Flats/Units/Townhouses/ Apartments/Houses Joined Together": 246, "Occupied Private Dwelling Not Further Defined": 102}, "2013 Census, number of bedrooms, for occupied private dwellings": {"One Bedroom": 87, "Five Bedrooms": 15, "Eight or More Bedrooms": 0, "Two Bedrooms": 213, "Three Bedrooms": 372, "Four Bedrooms": 81, "Seven Bedrooms": 3, "Total occupied private dwellings": 864, "Mean Number of Bedrooms": 2.7, "Six Bedrooms": 3, "Total dwellings stated": 771, "Not Elsewhere Included(3)": 93}, "2013 Census, number of rooms, for occupied private dwellings": {"Six Rooms": 189, "Eight or More Rooms": 54, "Total occupied private  dwellings": 864, "Five Rooms": 243, "Not Elsewhere Included(2)": 108, "One Room": 21, "Total dwellings stated": 756, "Four Rooms": 117, "Three Rooms": 33, "Seven Rooms": 63, "Two Rooms": 30}, "2013 Census, dwelling record type for occupied dwellings": {"Occupied Private Dwelling": 864, "Total occupied dwellings": 867, "Occupied Non-private Dwelling": 3}},
"census-family": 
{"2013 Census, total families in occupied private dwellings": 579, "2013 Census, total family income (grouped),(1)(2)(3) for families in occupied private dwellings": {"$30,001\u2013$50,000": 108, "$70,001\u2013$100,000": 90, "$20,000 or Less": 60, "Median family income ($)(5)(10)": 50100, "$100,001 or More": 54, "Total families in occupied private dwellings": 579, "$20,001\u2013$30,000": 63, "Total families stated": 459, "Not Stated(4)": 120, "$50,001\u2013$70,000": 84}, "Area Unit Code (2013 Areas)": "568201", "Area Unit Description": "Taita North", "2013 Census, family type, for families in occupied private dwellings": {"One parent with child(ren)": 165, "Couple without children": 150, "Couple with child(ren)": 264, "Total families in occupied private dwellings": 579}, "2013 Census, sources of family income,(6)(7)(8)(9) for families in occupied private dwellings": {"Other Sources of Income": 15, "Other Super., Pensions, Annuities": 9, "Domestic Purposes Benefit": 84, "Interest, Dividends, Rent, Other Invest.": 45, "Total families in private occupied dwellings": 579, "Not Stated": 18, "Total families stated": 564, "Invalids Benefit": 27, "Other Govt Benefits, Payments or Pension": 75, "Sickness Benefit": 33, "NZ Superannuation or Veterans Pension": 75, "Wages, Salary, Commissions, Bonuses etc": 411, "Unemployment Benefit": 42, "Student Allowance": 33, "Self-employment or Business": 54, "No Source of Income During That Time": 6, "Payments from a Work Accident Insurer": 9}},
"census-household": 
{"2013 Census, household composition, for households in occupied private dwellings": {"Two-family household (with or without other people)": 45, "Other multi-person household": 42, "Total households stated": 819, "Household composition unidentifiable": 42, "Total households in occupied private dwellings": 861, "One-family household (with or without other people)": 480, "One-person household": 249, "Three or more family household (with or without other people)": 3}, "2013 Census, total households in occupied private dwellings": 858, "2013 Census, number of motor vehicles, for households in occupied private dwellings": {"Two Motor Vehicles": 192, "Total households stated": 771, "Three or More Motor Vehicles": 51, "Total households in occupied private dwellings": 861, "No Motor Vehicle": 159, "Not Elsewhere Included(19)": 90, "One Motor Vehicle": 366}, "Area Unit Code (2013 Areas)": "568201", "2013 Census, number of usual residents in household,(1) for households in occupied private dwellings": {"Six Usual Residents": 36, "One Usual Resident": 246, "Five Usual Residents": 69, "Total households in occupied private dwellings": 861, "Eight or More Usual Residents": 27, "Mean Number of Usual Household Members": 2.9, "Two Usual Residents": 201, "Seven Usual Residents": 24, "Three Usual Residents": 132, "Four Usual Residents": 123}, "2013 Census, weekly rent paid, for households in rented occupied private dwellings(14)": {"Total households in rented occupied private dwellings": 429, "Total households stated": 381, "Not Elsewhere Included(17)": 48, "$250\u2013$299": 48, "$350 and Over": 30, "Median Weekly Rent Paid ($)(16)(18)": 150, "Under $100": 72, "$150\u2013$199": 39, "$100\u2013$149": 108, "$300\u2013$349": 51, "$200\u2013$249": 30}, "2013 Census, sector of landlord, for households in rented occupied private dwellings(14)": {"Not Elsewhere Included(15)": 30, "Total households in rented occupied private dwellings": 429, "Total households stated": 399, "Private Person, Trust or Business": 174, "Other State-Owned Corporation or State-Owned Enterprise or Government Department or Ministry": 6, "Local Authority or City Council": 6, "Housing New Zealand Corporation": 219}, "Area Unit Description": "Taita North", "2013 Census, access to telecommunications(20)(21), for households in occupied private dwellings": {"Total households stated": 765, "No Access to Telecommunication Systems": 27, "Access to a Cellphone/Mobile Phone": 609, "Access to the Internet": 453, "Total households in occupied private dwellings": 861, "Not Elsewhere Included(22)": 96, "Access to a Telephone": 561, "Access to a Fax Machine": 39}, "2013 Census, sources of household income,(6)(7)(8)(9) for households in occupied private dwellings": {"Other Super., Pensions, Annuities": 27, "Total households in occupied private dwellings": 861, "NZ Superannuation or Veterans Pension": 159, "Interest, Dividends, Rent, Other Invest.": 78, "Self-employment or Business": 63, "Student Allowance": 42, "Domestic Purposes Benefit": 87, "Wages, Salary, Commissions, Bonuses etc": 507, "Other Sources of Income": 21, "No Source of Income During That Time": 9, "Other Govt Benefits, Payments or Pension": 84, "Payments from a Work Accident Insurer": 12, "Invalids Benefit": 60, "Total Households Stated": 771, "Unemployment Benefit": 84, "Not Stated": 87, "Sickness Benefit": 60}, "2013 Census, total household income (grouped),(2)(3)(4) for households in occupied private dwellings": {"$30,001\u2013$50,000": 129, "$20,000 or Less": 144, "Total households stated": 633, "$70,001\u2013$100,000": 99, "Total households in occupied private dwellings": 858, "$50,001\u2013$70,000": 93, "$20,001\u2013$30,000": 93, "$100,001 or More": 81, "Median household income ($)(18)(23)": 41700, "Not Stated(5)": 228}, "2013 Census, tenure of household,(10) for households in occupied private dwellings": {"Dwelling Held in a Family Trust(13)": 36, "Total households stated": 759, "Dwelling Owned or Partly Owned": 267, "Total households in occupied private dwellings": 861, "Not Elsewhere Included(11)": 99, "Dwelling Not Owned and Not Held in a Family Trust(12)": 453}},
"census-individual-part-1": 
{"Area Unit Description": "Taita North", "2013 Census, six languages (total responses)(11), for the census usually resident population count(1)": {"Total people": 2610, "Samoan": 471, "NZ Sign Language": 27, "M\u0101ori": 156, "None (eg too young to talk)(13)": 45, "Not Elsewhere Included(12)": 291, "English": 2193, "Other": 318, "Total people stated": 2331}, "2013 Census, years at usual residence, for the census usually resident population count(1)": {"30 Years or More": 105, "Total people stated": 2313, "15\u201329 Years": 273, "10\u201314 Years": 285, "Total people": 2610, "1\u20134 Years": 723, "0 Years": 414, "5\u20139 Years": 513, "Not Elsewhere Included(4)": 297}, "2013 Census, census night population count(2)": 2577, "2013 Census, years since arrival in New Zealand, for the overseas\u2013born census usually resident population count(1)": {"30\u201339 Years": 60, "Total people stated": 603, "Not Elsewhere Included(6)": 42, "20\u201329 Years": 108, "50 Years or More": 30, "0\u20139 Years": 201, "40\u201349 Years": 60, "Total people": 648, "10\u201319 Years": 147}, "2013 Census, M\u0101ori descent, for the census usually resident population count(1)": {"No M\u0101ori Descent": 1482, "M\u0101ori Descent": 618, "Not Elsewhere Included(14)": 453, "Don't Know": 57, "Total people": 2610, "Total people stated": 2157}, "2013 Census, age in broad groups, for the census usually resident population count(1)": {"15\u201364 Years": 1626, "65 years and Over": 324, "Total people": 2610, "Under 15 years": 660}, "2013 Census, census usually resident population count(1)": 2610, "Area Unit Code (2013 Areas)": "568201", "2013 Census, birthplace, for the census usually resident population count(1)": {"Not Elsewhere Included(5)": 273, "Overseas born": 648, "Total people": 2610, "NZ born": 1689, "Total people stated": 2337}, "2013 Census, age in five-year groups, for the census usually resident population count(1)": {"15\u201319 Years": 210, "65 years and Over": 324, "Median Age(3)": 33.4, "35\u201339 Years": 198, "5\u20139 Years": 222, "40\u201344 Years": 153, "10\u201314 Years": 225, "55\u201359 Years": 123, "20\u201324 Years": 183, "0\u20134 Years": 210, "50\u201354 Years": 162, "60\u201364 Years": 138, "Total people": 2610, "30\u201334 Years": 150, "45\u201349 Years": 150, "25\u201329 Years": 153}, "2013 Census, ethnic group (grouped total responses)(7)(8), for the census usually resident population count(1)": {"MELAA(9)": 42, "Pacific Peoples": 909, "Other(10)": 36, "European": 969, "Not Elsewhere Included": 237, "Total people stated": 2373, "Total people": 2610, "M\u0101ori": 633, "Asian": 195}, "2013 Census, usual residence five years ago (2008) indicator, for the census usually resident population count(1)": {"Total people": 2610, "Elsewhere in New Zealand": 870, "Not Born Five Years Ago": 210, "No Fixed Abode Five Years Ago": 0, "Same as Usual Residence": 1065, "Not Elsewhere Included": 363, "Total people stated": 2247, "Overseas": 102}, "2013 Census, sex, for the census usually resident population count(1)": {"Male": 1278, "Female": 1332, "Total people": 2610}},
"census-individual-part-2": 
{"Area Unit Description": "Taita North", "2013 Census, study participation,(18) for the census usually resident population count aged 15 years and over(1)": {"Full-time Study(19)": 186, "Not Studying": 1353, "Total people": 1950, "Part-time Study(20)": 60, "Not stated": 348, "Total people stated": 1599, "Full-time and Part-time Study": 0}, "2013 Census, legally registered relationship status, for the census usually resident population count aged 15 years and over(1)": {"Married (not separated)": 627, "Never married and never in a civil union": 684, "Separated/divorced or dissolved/widowed/surviving partner(6)(7)(8)": 297, "Total people stated": 1608, "Total people": 1950, "Not Elsewhere Included(9)": 339}, "2013 Census, highest qualification,(15) for the census usually resident population count aged 15 years and over(1)": {"Level 4 Certificate": 144, "Doctorate Degree": 0, "Masters Degree": 18, "Level 2 Certificate": 171, "Total people stated": 1545, "Overseas Secondary School Qualification": 120, "Level 1 Certificate": 213, "Bachelor Degree and Level 7 Qualifications": 90, "Level 3 Certificate": 150, "Postgraduate and Honours Degrees": 12, "No Qualification": 555, "Total people": 1950, "Not Elsewhere Included(17)": 405, "Level 5 or Level 6 Diploma(16)": 75}, "2013 Census, number of children born alive,(13) for the female census usually resident population count aged 15 years and over(1)": {"Five Children": 36, "Object to Answering": 42, "One Child": 105, "Not Elsewhere Included(14)": 138, "Four Children": 90, "Six or More Children": 54, "No Children": 261, "Total people stated": 873, "Three Children": 135, "Two Children": 156, "Total people": 1011}, "2013 Census, tenure holder,(10) for the census usually resident population count aged 15 years and over(1)": {"Not Elsewhere Included(12)": 180, "Own or Partly Own Usual Residence(11)": 504, "Total people stated": 1767, "Do Not Own Usual Residence": 1263, "Total people": 1950}, "Area Unit Code (2013 Areas)": "568201", "2013 Census, total personal income (grouped),(21)(22) for the census usually resident population count aged 15 years and over(1)": {"$5,000 or Less": 303, "$30,001\u2013$50,000": 375, "$5,001\u2013$10,000": 111, "Median personal income ($)(23)(27)": 20900, "Total people": 1947, "Total people stated": 1560, "$20,001\u2013$30,000": 249, "Not stated": 390, "$50,001 or More": 180, "$10,001\u2013$20,000": 345}, "2013 Census, partnership status in current relationship, for the census usually resident population count aged 15 years and over(1)": {"Total people": 1950, "Partnered": 852, "Not stated": 258, "Total people stated": 1692, "Non-Partnered": 843}, "2013 Census, cigarette smoking behaviour,(4) for the census usually resident population count aged 15 years and over(1)": {"Not Elsewhere Included(5)": 288, "Regular Smoker": 447, "Total people stated": 1662, "Total people": 1950, "Ex-Smoker": 333, "Never Smoked Regularly": 882}, "2013 Census, sources of personal income(24)(25)(26) for the census usually resident population count aged 15 years and over": {"Self-employment or Business": 78, "Wages, Salary, Commissions, Bonuses etc": 888, "Other Sources of Income": 27, "Total people Stated": 1674, "No Source of Income During That Time": 168, "Not stated": 276, "Sickness Benefit": 75, "Total people": 1947, "Invalids Benefit": 78, "NZ Superannuation or Veterans Pension": 261, "Payments from a Work Accident Insurer": 12, "Other Super., Pensions, Annuities": 36, "Other Govt Benefits, Payments or Pension": 93, "Domestic Purposes Benefit": 96, "Unemployment Benefit": 108, "Student Allowance": 51, "Interest, Dividends, Rent, Other Invest.": 111}, "2013 Census, religious affiliation (total responses),(2) for the census usually resident population count(1)": {"Object to Answering": 132, "Judaism/ Jewish": 9, "Hindu": 42, "Islam/Muslim": 36, "Total people stated": 2247, "Total people": 2610, "Buddhist": 36, "Not Elsewhere Included(3)": 366, "No Religion": 588, "M\u00e4ori Christian": 51, "Other Religions": 24, "Spiritualism and New Age Religions": 6, "Christian": 1371}},
"census-individual-part-3a": 
{"2013 Census, occupation (NZSCO99 major group),(11)(12) for workplace address,(9)(10) for the employed census usually resident population count aged 15 years and over(1)": {"Legislators, Administrators and Managers": 48, "Clerks": 27, "Plant and Machine Operators and Assemblers": 21, "Service and Sales Workers": 66, "Agriculture and Fishery Workers": 3, "Professionals": 117, "Elementary Occupations (incl Residuals)(13)": 39, "Technicians and Associate Professionals": 60, "Total people(14)": 396, "Trades Workers": 21}, "2013 Census, work and labour force status,(2) for the census usually resident population count aged 15 years and over(1)": {"Not in the Labour Force": 699, "Unemployed": 159, "Employed Part-time": 192, "Total people": 1950, "Total people stated": 1779, "Work and Labour Force Status Unidentifiable": 174, "Employed Full-time": 726}, "2013 Census, occupation (NZSCO99 major group),(11)(12) for the employed census usually resident population count aged 15 years and over(1)": {"Legislators, Administrators and Managers": 60, "Clerks": 102, "Plant and Machine Operators and Assemblers": 108, "Service and Sales Workers": 156, "Agriculture and Fishery Workers": 6, "Professionals": 93, "Elementary Occupations (incl Residuals)(13)": 213, "Technicians and Associate Professionals": 102, "Total people(14)": 921, "Trades Workers": 78}, "2013 Census, occupation (ANZSCO major group),(6)(7) for workplace address,(9)(10) for the employed census usually resident population count aged 15 years and over(1)": {"Technicians and Trades Workers": 36, "Total people": 393, "Not Elsewhere Included(8)": 18, "Total people stated": 378, "Labourers": 33, "Clerical and Administrative Workers": 36, "Sales Workers": 9, "Professionals": 144, "Managers": 42, "Community and Personal Service Workers": 66, "Machinery Operators and Drivers": 12}, "2013 Census, occupation (ANZSCO major group),(6)(7) for the employed census usually resident population count aged 15 years and over(1)": {"Technicians and Trades Workers": 123, "Total people": 918, "Not Elsewhere Included(8)": 90, "Total people stated": 831, "Labourers": 144, "Clerical and Administrative Workers": 105, "Sales Workers": 72, "Professionals": 111, "Managers": 60, "Community and Personal Service Workers": 117, "Machinery Operators and Drivers": 96}, "2013 Census, industry (ANZSIC06 division),(15)(16) for the employed census usually resident population count aged 15 years and over(1)": {"Administrative and Support Services": 51, "Total people stated": 843, "Construction": 66, "Arts and Recreation Services": 9, "Public Administration and Safety": 63, "Transport, Postal and Warehousing": 75, "Not Elsewhere Included(17)": 75, "Mining": 0, "Manufacturing": 111, "Financial and Insurance Services": 27, "Information Media and Telecommunications": 6, "Professional, Scientific and Technical Services": 39, "Rental, Hiring and Real Estate Services": 9, "Electricity, Gas, Water and Waste Services": 9, "Total people": 918, "Education and Training": 54, "Health Care and Social Assistance": 120, "Other Services": 42, "Wholesale Trade": 27, "Agriculture, Forestry and Fishing": 0, "Accommodation and Food Services": 51, "Retail Trade": 81}, "2013 Census, industry (ANZSIC96 division),(18)(19) for workplace address,(9)(10) for the employed census usually resident population count aged 15 years and over(1)": {"Construction": 12, "Cultural and Recreational Services": 3, "Mining": 0, "Total people stated": 387, "Manufacturing": 24, "Communication Services": 3, "Government Administration and Defence": 0, "Electricity, Gas and Water Supply": 0, "Transport and Storage": 12, "Property and Business Services": 27, "Finance and Insurance": 0, "Personal and Other Services": 15, "Total people": 393, "Accommodation, Cafes and Restaurants": 3, "Not Elsewhere Included(20)": 9, "Wholesale Trade": 3, "Agriculture, Forestry and Fishing": 0, "Retail Trade": 21, "Education": 162, "Health and Community Services": 99}, "Area Unit Description": "Taita North", "2013 Census, status in employment,(3)(4) for the employed census usually resident population count aged 15 years and over(1)": {"Self-Employed and Without Employees": 60, "Paid Employee": 792, "Total people": 918, "Total people stated": 867, "Unpaid Family Worker": 6, "Employer": 9, "Not Elsewhere Included(5)": 54}, "2013 Census, industry (ANZSIC96 division),(18)(19) for the employed census usually resident population count aged 15 years and over(1)": {"Property and Business Services": 93, "Cultural and Recreational Services": 9, "Health and Community Services": 120, "Total people stated": 840, "Manufacturing": 111, "Communication Services": 15, "Government Administration and Defence": 45, "Electricity, Gas and Water Supply": 3, "Mining": 0, "Construction": 66, "Finance and Insurance": 27, "Personal and Other Services": 60, "Total people": 918, "Accommodation, Cafes and Restaurants": 36, "Not Elsewhere Included(20)": 78, "Wholesale Trade": 36, "Agriculture, Forestry and Fishing": 0, "Retail Trade": 102, "Education": 54, "Transport and Storage": 63}, "2013 Census, industry (ANZSIC06 division),(15)(16) for workplace address,(9)(10) for the employed census usually resident population count aged 15 years and over(1)": {"Administrative and Support Services": 6, "Total people stated": 387, "Construction": 12, "Arts and Recreation Services": 0, "Public Administration and Safety": 3, "Transport, Postal and Warehousing": 12, "Not Elsewhere Included(17)": 9, "Mining": 0, "Manufacturing": 24, "Financial and Insurance Services": 0, "Information Media and Telecommunications": 0, "Professional, Scientific and Technical Services": 9, "Rental, Hiring and Real Estate Services": 15, "Electricity, Gas, Water and Waste Services": 0, "Total people": 396, "Education and Training": 159, "Health Care and Social Assistance": 99, "Other Services": 27, "Wholesale Trade": 3, "Agriculture, Forestry and Fishing": 0, "Accommodation and Food Services": 6, "Retail Trade": 9}, "Area Unit Code (2013 Areas)": "568201"},
"census-individual-part-3b": 
{"2013 Census, hours worked in employment per week,(2)(3) for the employed census usually resident population count aged 15 years and over(1)": {"1\u20139 Hours Worked": 36, "30\u201339 Hours Worked": 144, "Total people stated": 828, "Not Elsewhere Included(4)": 93, "Total people": 921, "10\u201319 Hours Worked": 45, "20\u201329 Hours Worked": 78, "40\u201349 Hours Worked": 429, "50\u201359 Hours Worked": 48, "60 Hours or More  Worked": 45}, "Area Unit Code (2013 Areas)": "568201", "2013 Census, main means of travel to work, for the employed census usually resident population count aged 15 years and over(1)": {"Drove a Private Car, Truck or Van": 411, "Total people stated": 840, "Train": 84, "Motor Cycle or Power Cycle": 3, "Public Bus": 60, "Other": 6, "Total people": 918, "Worked at Home": 21, "Walked or Jogged": 36, "Drove a Company Car, Truck or Van": 60, "Passenger in a Car, Truck, Van or Company Bus": 72, "Bicycle": 6, "Did Not Go to Work Today": 84, "Not Elsewhere Included(5)": 81}, "Area Unit Description": "Taita North", "2013 Census, unpaid activities(8)(9) for the census usually resident population count aged 15 years and over(1)": {"No Activities": 243, "Total people stated": 1599, "Looking After a Child Who is a Member of Own Household": 585, "Looking After a Child Who Does Not Live in Own Household": 309, "Household Work, Cooking, Repairs, Gardening, etc, for Own Household": 1281, "Looking After a Member of Own Household Who is Ill or Has a Disability": 189, "Helping Someone Who is Ill or Has a Disability Who Does Not Live in Own Household": 174, "Other Helping or Voluntary Work for or Through Any Organisation, Group or Marae": 264, "Total people": 1950, "Not Elsewhere Included(10)": 351}, "2013 Census, main means of travel to work, for workplace address,(6)(7) for the employed census usually resident population count aged 15 years and over(1)": {"Drove a Private Car, Truck or Van": 207, "Total people stated": 384, "Train": 9, "Motor Cycle or Power Cycle": 3, "Public Bus": 12, "Other": 6, "Total people": 396, "Worked at Home": 15, "Walked or Jogged": 33, "Drove a Company Car, Truck or Van": 30, "Passenger in a Car, Truck, Van or Company Bus": 21, "Bicycle": 9, "Did Not Go to Work Today": 42, "Not Elsewhere Included(5)": 12}},
"crime": 
{"Region_2013_label": "Wellington Region", "Index": "573", "Urban_area_type": "Main urban area", "Urban_area_2013_code": "18", "Area_unit_2013_label": "Taita North", "Urban_area_2013_label": "Lower Hutt Zone", " Rate_per_10000_population ": "40", "Territorial_authority_area_2013_code": "46", "Region_2013_code": "9", " Rate_ratio_NZ_average_rate ": "0.8", "Area_unit_2013_code": "568201", "Territorial_authority_area_2013_label": "Lower Hutt City", "Victimisations_calendar_year_2015": "11", "Population_mid_point_2015": "2750"}}
